Workbook
Name projeto_val: '1.Identificacao'!C3
Name produtor_val: '1.Identificacao'!C4
Name unidade_val: '1.Identificacao'!C5
Name municipio_val: '1.Identificacao'!C6
Name data_val: '1.Identificacao'!C7
Name template_val: '1.Identificacao'!C9
Name fiscal_val: '1.Identificacao'!C10
Name produto_nome: '2.Receita'!C3
Name qtd_val: '2.Receita'!C4
Name prod_val: '2.Receita'!C5
Name preco_val: '2.Receita'!C6
Name sec_desc_val: '2.Receita'!C9
Name sec_valor_val: '2.Receita'!E9
Name comerc_pct: '2.Receita'!C12
Name rb_val: '2.Receita'!C15
Name comerc_rs: '2.Receita'!C16
Name funrural_rs: '2.Receita'!C17
Name rl_val: '2.Receita'!C18
Name modo_val: '3.Manejo'!C3
Name subtotal_coe: '4.COE'!H25
Name seguro_pct: '4.COE'!C27
Name ater_pct: '4.COE'!C28
Name juros_pct: '4.COE'!C29
Name seguro_rs: '4.COE'!E27
Name ater_rs: '4.COE'!E28
Name juros_rs: '4.COE'!E29
Name coe_total: '4.COE'!H31
Name cultura_val: '5.Implantacao'!C5
Name form_anos: '5.Implantacao'!C6
Name vida_util: '5.Implantacao'!C7
Name invest_ha: '5.Implantacao'!G27
Name area_impl: '5.Implantacao'!G28
Name invest_total: '5.Implantacao'!G29
Name dep_formacao: '5.Implantacao'!G31
Name dep_bens: '6.Fixos'!G16
Name dep_total: '6.Fixos'!G18
Name cap_medio: '6.Fixos'!G22
Name prol_val: '6.Fixos'!C25
Name outros_fixos: '6.Fixos'!C26
Name taxa_cap: '6.Fixos'!C27
Name arrend: '6.Fixos'!C28
Name area_fixos: '6.Fixos'!C29
Name rem_cap: '6.Fixos'!G25
Name rem_terra: '6.Fixos'!G26
Name cot_val: '6.Fixos'!G35
Name ct_val: '6.Fixos'!G38
Name margem_bruta: '7.Resultado'!C6
Name margem_liq: '7.Resultado'!C8
Name resultado_final: '7.Resultado'!C10
Name custo_form: '7.Resultado'!C22
Name taxa_desc: '7.Resultado'!C23
Name vpl_val: '7.Resultado'!C68
Name tir_val: '7.Resultado'!C69

Sheet Ref
A1: Codigo | B1: Nome | C1: Unidade | D1: LblQtd | E1: LblProd | F1: UnProd | G1: UnPreco | H1: Familia | I1: Modo | J1: Perene | K1: Giro | M1: Familia | N1: Categoria | P1: Codigo | Q1: Nome | R1: Form | S1: Vida | U1: Fiscal | V1: Aliquota
A2: graos | B2: Grãos e cereais | C2: ha | D2: Área | E2: Produtividade | F2: sc/ha | G2: R$/sc | H2: lavoura | I2: A | J2: 0 | K2: 0 | M2: lavoura | N2: Sementes/mudas | P2: uva | Q2: Uva | R2: 3 | S2: 20 | U2: PF | V2: 0.0163 | X2: Agrotóxicos
A3: fumo | B3: Fumo (tabaco) | C3: ha | D3: Área | E3: Produtividade | F3: @/ha | G3: R$/@ | H3: lavoura | I3: A | J3: 0 | K3: 0 | M3: lavoura | N3: Fertilizantes | P3: maca | Q3: Maçã | R3: 4 | S3: 20 | U3: PJ | V3: 0.0223 | X3: Alimentação
A4: horta | B4: Horta / olericultura | C4: ha | D4: Área | E4: Produtividade | F4: kg/ha | G4: R$/kg | H4: lavoura | I4: A | J4: 0 | K4: 0 | M4: lavoura | N4: Corretivos | P4: citros | Q4: Citros | R4: 3 | S4: 20 | X4: Alimentação suplementar
A5: fruta | B5: Fruticultura | C5: ha | D5: Área | E5: Produtividade | F5: kg/ha | G5: R$/kg | H5: lavoura | I5: B | J5: 1 | K5: 0 | M5: lavoura | N5: Agrotóxicos | P5: pessego | Q5: Pêssego | R5: 3 | S5: 12 | X5: Aquisição de animais (giro)
A6: ervamate | B6: Erva-mate | C6: ha | D6: Área | E6: Produtividade | F6: kg/ha | G6: R$/kg | H6: lavoura | I6: B | J6: 1 | K6: 0 | M6: lavoura | N6: Operações/mecanização | P6: erva | Q6: Erva-mate | R6: 5 | S6: 30 | X6: Corretivos
A7: madeira | B7: Silvicultura | C7: ha | D7: Área | E7: Produtividade | F7: m³/ha | G7: R$/m³ | H7: lavoura | I7: H | J7: 1 | K7: 0 | M7: lavoura | N7: Mão de obra | P7: peca | Q7: Noz-pecã | R7: 7 | S7: 40 | X7: Embalagens e materiais
A8: corte | B8: Corte / confinamento | C8: cabeça | D8: Cabeças (giro) | E8: Peso de venda | F8: kg PV/cab | G8: R$/kg vivo | H8: criacao | I8: D | J8: 0 | K8: 1 | M8: lavoura | N8: Outros | P8: oliveira | Q8: Oliveira | R8: 4 | S8: 30 | X8: Energia e aquecimento
A9: leite | B9: Leite | C9: vaca | D9: Vacas em lactação | E9: Produção | F9: L/vaca/ano | G9: R$/L | H9: criacao | I9: C | J9: 0 | K9: 0 | M9: criacao | N9: Alimentação | P9: eucalipto | Q9: Eucalipto | R9: 7 | S9: 7 | X9: Energia/água
A10: cria | B10: Cria (bovinos) | C10: matriz | D10: Matrizes | E10: Produção | F10: kg terneiro/matriz/ano | G10: R$/kg | H10: criacao | I10: C | J10: 0 | K10: 0 | M10: criacao | N10: Sanidade | X10: Fertilizantes
A11: ovinos | B11: Ovinos | C11: matriz | D11: Matrizes (ovelhas) | E11: Produção | F11: kg PV/matriz/ano | G11: R$/kg PV | H11: criacao | I11: C | J11: 0 | K11: 0 | M11: criacao | N11: Aquisição de animais (giro) | X11: Insumos
A12: suinos | B12: Suínos | C12: cabeça | D12: Cabeças alojadas | E12: Peso de abate | F12: kg/cab | G12: R$/kg | H12: criacao | I12: D | J12: 0 | K12: 1 | M12: criacao | N12: Mão de obra | X12: Materiais e embalagens
A13: aves_corte | B13: Aves de corte | C13: cabeça | D13: Cabeças alojadas | E13: Peso de abate | F13: kg/cab | G13: R$/kg | H13: criacao | I13: D | J13: 0 | K13: 1 | M13: criacao | N13: Energia/água | X13: Mão de obra
A14: aves_postura | B14: Galinhas poedeiras | C14: matriz | D14: Matrizes (galinhas) | E14: Produção | F14: dúzias/matriz/ano | G14: R$/dúzia | H14: postura | I14: G | J14: 0 | K14: 0 | M14: criacao | N14: Outros | X14: Operações
A15: apicultura | B15: Apicultura | C15: colmeia | D15: Colmeias | E15: Produção | F15: kg mel/colmeia/ano | G15: R$/kg | H15: apicultura | I15: F | J15: 0 | K15: 0 | M15: apicultura | N15: Alimentação suplementar | X15: Operações/mecanização
A16: tilapia | B16: Tilápia | C16: tanque | D16: Tanques | E16: Produção | F16: kg/tanque | G16: R$/kg | H16: criacao | I16: D | J16: 0 | K16: 1 | M16: apicultura | N16: Sanidade | X16: Outros
A17: outra | B17: Outra | C17: unidade | D17: Unidades | E17: Produtividade | F17: un. | G17: R$/un. | H17: outra | I17: E | J17: 0 | K17: 0 | M17: apicultura | N17: Rainha e enxames | X17: Rainha e enxames
M18: apicultura | N18: Materiais e embalagens | X18: Ração e suplementos
M19: apicultura | N19: Mão de obra | X19: Sanidade
M20: apicultura | N20: Outros | X20: Sementes/mudas
M21: postura | N21: Ração e suplementos
M22: postura | N22: Sanidade
M23: postura | N23: Energia e aquecimento
M24: postura | N24: Embalagens e materiais
M25: postura | N25: Mão de obra
M26: postura | N26: Outros
M27: outra | N27: Insumos
M28: outra | N28: Mão de obra
M29: outra | N29: Operações
M30: outra | N30: Outros

Sheet 1.Identificacao
B1: 1. IDENTIFICAÇÃO DO PROJETO
B3: Título do projeto:
B4: Produtor:
B5: Unidade de produção:
B6: Município:
B7: Data:
B9: Template (atividade): | C9: graos
B10: Enquadramento fiscal: | C10: PF
B12: CRÉDITO RURAL
B13: Usa crédito?
B14: Finalidade:
B15: Enquadramento:
B16: Documentos organizados?
B17: Módulos fiscais:
B18: Localização:
B20: DIAGNÓSTICO ESTRATÉGICO (SWOT)
B21: Forças:
B22: Fraquezas:
B23: Oportunidades:
B24: Ameaças:
C1313: nao
C1616: nao

Sheet 2.Receita
B1: 2. PRODUÇÃO E RECEITA
B3: Produto / Cultura:
B4: Unidades de produção: | C4: 0 | D4: Unidade: | E4: =VLOOKUP(template_val,Ref!$A$1:$K$17,3,FALSE)
B5: Produtividade: | C5: 0 | D5: Unidade: | E5: =VLOOKUP(template_val,Ref!$A$1:$K$17,6,FALSE)
B6: Preço: | C6: 0 | D6: Unidade: | E6: =VLOOKUP(template_val,Ref!$A$1:$K$17,7,FALSE)
B8: OUTRAS RECEITAS
B9: Descrição: | D9: Valor (R$): | E9: 0
B11: DEDUÇÕES DA RECEITA
B12: Comercialização (%): | C12: 0
B13: Funrural (%): | C13: =VLOOKUP(fiscal_val,Ref!$U$1:$V$3,2,FALSE)
B15: RECEITA BRUTA (RB): | C15: =qtd_val*prod_val*preco_val+sec_valor_val
B16: (−) Comercialização: | C16: =rb_val*(comerc_pct/100)
B17: (−) Funrural: | C17: =rb_val*C13
B18: RECEITA LÍQUIDA (RL): | C18: =rb_val-comerc_rs-funrural_rs
B20: Fórmula: Qtd × Produtividade × Preço + Outras receitas

Sheet 3.Manejo
B1: 3. PRÁTICAS DE MANEJO
B3: Modo de manejo: | C3: =VLOOKUP(template_val,Ref!$A$1:$K$17,9,FALSE)
B5: Sistema / Espécie / Categoria:
B6: Variedade / Cultivar:
B7: Mês de início / Plantio:
B8: Mês de colheita / Final:
B9: Adubação / Dieta / Ração:
B10: Sanidade / Tratamentos:
B11: Irrigação / Instalações:
B12: Outras práticas:
B14: Observações detalhadas:

Sheet 4.COE
B1: 4. CUSTEIO (COE)
B3: Nº | C3: Descrição | D3: Categoria | E3: Unidade | F3: Qtd/Un | G3: Preço Unit (R$) | H3: Custo/Un (R$) | I3: Custo Total (R$)
B4: 1 | F4: 0 | G4: 0 | H4: =IF(AND(F4>0,G4>0),F4*G4,0) | I4: =IF(H4>0,H4*qtd_val,0)
B5: 2 | F5: 0 | G5: 0 | H5: =IF(AND(F5>0,G5>0),F5*G5,0) | I5: =IF(H5>0,H5*qtd_val,0)
B6: 3 | F6: 0 | G6: 0 | H6: =IF(AND(F6>0,G6>0),F6*G6,0) | I6: =IF(H6>0,H6*qtd_val,0)
B7: 4 | F7: 0 | G7: 0 | H7: =IF(AND(F7>0,G7>0),F7*G7,0) | I7: =IF(H7>0,H7*qtd_val,0)
B8: 5 | F8: 0 | G8: 0 | H8: =IF(AND(F8>0,G8>0),F8*G8,0) | I8: =IF(H8>0,H8*qtd_val,0)
B9: 6 | F9: 0 | G9: 0 | H9: =IF(AND(F9>0,G9>0),F9*G9,0) | I9: =IF(H9>0,H9*qtd_val,0)
B10: 7 | F10: 0 | G10: 0 | H10: =IF(AND(F10>0,G10>0),F10*G10,0) | I10: =IF(H10>0,H10*qtd_val,0)
B11: 8 | F11: 0 | G11: 0 | H11: =IF(AND(F11>0,G11>0),F11*G11,0) | I11: =IF(H11>0,H11*qtd_val,0)
B12: 9 | F12: 0 | G12: 0 | H12: =IF(AND(F12>0,G12>0),F12*G12,0) | I12: =IF(H12>0,H12*qtd_val,0)
B13: 10 | F13: 0 | G13: 0 | H13: =IF(AND(F13>0,G13>0),F13*G13,0) | I13: =IF(H13>0,H13*qtd_val,0)
B14: 11 | F14: 0 | G14: 0 | H14: =IF(AND(F14>0,G14>0),F14*G14,0) | I14: =IF(H14>0,H14*qtd_val,0)
B15: 12 | F15: 0 | G15: 0 | H15: =IF(AND(F15>0,G15>0),F15*G15,0) | I15: =IF(H15>0,H15*qtd_val,0)
... B23: 20 | F23: 0 | G23: 0 | H23: =IF(AND(F23>0,G23>0),F23*G23,0) | I23: =IF(H23>0,H23*qtd_val,0)
B25: Subtotal dos itens diretos: | H25: =SUM(I4:I23)
B27: Seguro (%): | E27: =H25*(seguro_pct/100)
B28: Assistência Técnica (%): | E28: =H25*(ater_pct/100)
B29: Juros de custeio (%): | E29: =H25*(juros_pct/100)
B31: COE TOTAL: | H31: =H25+E27+E28+E29
B33: Preencha apenas as colunas em AMARELO. As demais calculam automaticamente.
C2727: 0
C2828: 0
C2929: 0

Sheet 5.Implantacao
B1: 5. IMPLANTAÇÃO (CULTURAS PERENES)
B3: É cultura perene? | C3: =IF(VLOOKUP(template_val,Ref!$A$1:$K$17,10,FALSE)=1,"SIM — Preencha esta aba","NÃO — Opcional")
B5: Cultura perene: | C5: uva
B6: Anos de formação: | C6: 0
B7: Vida útil produtiva (anos): | C7: 0
B9: ITENS DE IMPLANTAÇÃO (por ha)
B10: Nº | C10: Descrição | D10: Unidade | E10: Qtd/ha | F10: Preço Unit (R$) | G10: Custo/ha (R$)
B11: 1 | E11: 0 | F11: 0 | G11: =IF(AND(E11>0,F11>0),E11*F11,0)
B12: 2 | E12: 0 | F12: 0 | G12: =IF(AND(E12>0,F12>0),E12*F12,0)
B13: 3 | E13: 0 | F13: 0 | G13: =IF(AND(E13>0,F13>0),E13*F13,0)
B14: 4 | E14: 0 | F14: 0 | G14: =IF(AND(E14>0,F14>0),E14*F14,0)
B15: 5 | E15: 0 | F15: 0 | G15: =IF(AND(E15>0,F15>0),E15*F15,0)
B16: 6 | E16: 0 | F16: 0 | G16: =IF(AND(E16>0,F16>0),E16*F16,0)
B17: 7 | E17: 0 | F17: 0 | G17: =IF(AND(E17>0,F17>0),E17*F17,0)
B18: 8 | E18: 0 | F18: 0 | G18: =IF(AND(E18>0,F18>0),E18*F18,0)
B19: 9 | E19: 0 | F19: 0 | G19: =IF(AND(E19>0,F19>0),E19*F19,0)
B20: 10 | E20: 0 | F20: 0 | G20: =IF(AND(E20>0,F20>0),E20*F20,0)
B21: 11 | E21: 0 | F21: 0 | G21: =IF(AND(E21>0,F21>0),E21*F21,0)
B22: 12 | E22: 0 | F22: 0 | G22: =IF(AND(E22>0,F22>0),E22*F22,0)
... B25: 15 | E25: 0 | F25: 0 | G25: =IF(AND(E25>0,F25>0),E25*F25,0)
B27: Investimento por ha: | G27: =SUM(G11:G25)
B28: Área implantada (ha): | G28: =qtd_val
B29: INVESTIMENTO TOTAL (ano 0): | G29: =G27*G28
B31: Depreciação anual da formação (automática): | G31: =IF(AND(G28>0,vida_util>0),G29/vida_util,0)

Sheet 6.Fixos
B1: 6. CUSTOS FIXOS E REMUNERAÇÃO DOS FATORES
B3: DEPRECIAÇÃO (BENS DE CAPITAL)
B4: Nº | C4: Descrição | D4: Aquisição (R$) | E4: Residual (R$) | F4: Vida útil (anos) | G4: Depreciação anual (R$) | H4: Capital médio (R$)
B5: 1 | D5: 0 | E5: 0 | F5: 0 | G5: =IF(AND(D5>0,F5>0),MAX(0,(D5-E5)/F5),0) | H5: =IF(D5>0,(D5+E5)/2,0)
B6: 2 | D6: 0 | E6: 0 | F6: 0 | G6: =IF(AND(D6>0,F6>0),MAX(0,(D6-E6)/F6),0) | H6: =IF(D6>0,(D6+E6)/2,0)
B7: 3 | D7: 0 | E7: 0 | F7: 0 | G7: =IF(AND(D7>0,F7>0),MAX(0,(D7-E7)/F7),0) | H7: =IF(D7>0,(D7+E7)/2,0)
B8: 4 | D8: 0 | E8: 0 | F8: 0 | G8: =IF(AND(D8>0,F8>0),MAX(0,(D8-E8)/F8),0) | H8: =IF(D8>0,(D8+E8)/2,0)
B9: 5 | D9: 0 | E9: 0 | F9: 0 | G9: =IF(AND(D9>0,F9>0),MAX(0,(D9-E9)/F9),0) | H9: =IF(D9>0,(D9+E9)/2,0)
B10: 6 | D10: 0 | E10: 0 | F10: 0 | G10: =IF(AND(D10>0,F10>0),MAX(0,(D10-E10)/F10),0) | H10: =IF(D10>0,(D10+E10)/2,0)
B11: 7 | D11: 0 | E11: 0 | F11: 0 | G11: =IF(AND(D11>0,F11>0),MAX(0,(D11-E11)/F11),0) | H11: =IF(D11>0,(D11+E11)/2,0)
B12: 8 | D12: 0 | E12: 0 | F12: 0 | G12: =IF(AND(D12>0,F12>0),MAX(0,(D12-E12)/F12),0) | H12: =IF(D12>0,(D12+E12)/2,0)
B13: 9 | D13: 0 | E13: 0 | F13: 0 | G13: =IF(AND(D13>0,F13>0),MAX(0,(D13-E13)/F13),0) | H13: =IF(D13>0,(D13+E13)/2,0)
B14: 10 | D14: 0 | E14: 0 | F14: 0 | G14: =IF(AND(D14>0,F14>0),MAX(0,(D14-E14)/F14),0) | H14: =IF(D14>0,(D14+E14)/2,0)
B16: Depreciação bens de capital: | G16: =SUM(G5:G14)
B17: Depreciação formação (automática): | G17: =dep_formacao
B18: DEPRECIAÇÃO TOTAL: | G18: =G16+G17
B20: Capital médio bens: | G20: =SUM(H5:H14)
B21: (+) Capital médio formação (invest/2): | G21: =IF(invest_total>0,invest_total/2,0)
B22: CAPITAL MÉDIO TOTAL: | G22: =G20+G21
B24: OUTROS FIXOS E REMUNERAÇÃO
B25: Pró-labore anual (R$): | E25: Remuneração do capital: | G25: =IF(AND(cap_medio>0,taxa_cap>0),cap_medio*(taxa_cap/100),0)
B26: Outros fixos (R$): | E26: Remuneração da terra: | G26: =IF(AND(arrend>0,area_fixos>0),arrend*area_fixos,0)
B27: Taxa remuneração capital (% a.a.):
B28: Arrendamento (R$/ha):
B29: Área para arrendamento (ha): | C29: =qtd_val
B31: COE (do passo 4): | G31: =coe_total
B32: (+) Depreciação total: | G32: =dep_total
B33: (+) Pró-labore: | G33: =prol_val
B34: (+) Outros fixos: | G34: =outros_fixos
B35: COT: | G35: =G31+G32+G33+G34
B36: (+) Remuneração do capital: | G36: =rem_cap
B37: (+) Remuneração da terra: | G37: =rem_terra
B38: CT (CUSTO TOTAL): | G38: =G35+G36+G37
C2525: 0
C2626: 0
C2727: 0
C2828: 0

Sheet 7.Resultado
B1: 7. RESULTADO E INDICADORES
B3: RESULTADO POR NÍVEL
B4: Receita Líquida (RL): | C4: =rl_val
B5: (−) COE: | C5: =coe_total
B6: Margem Bruta: | C6: =C4-C5
B7: (−) Fixos (COT − COE): | C7: =cot_val-coe_total
B8: Margem Líquida: | C8: =C6-C7
B9: (−) Fatores (CT − COT): | C9: =ct_val-cot_val
B10: RESULTADO: | C10: =C8-C9
B12: INDICADORES ECONÔMICOS
B13: Produtividade de nivelamento: | C13: =IF(AND(qtd_val>0,preco_val>0),coe_total/(qtd_val*preco_val),0)
B14: Preço de nivelamento: | C14: =IF(AND(qtd_val>0,prod_val>0),coe_total/(qtd_val*prod_val),0)
B15: Margem de segurança: | C15: =IF(AND(prod_val>0,B13>0),(prod_val-B13)/prod_val,0)
B16: Lucratividade: | C16: =IF(rb_val>0,resultado_final/rb_val,0)
B17: Rentabilidade (ROI): | C17: =IF(coe_total>0,resultado_final/coe_total,0)
B18: Eficiência econômica (RB/CT): | C18: =IF(ct_val>0,rb_val/ct_val,0)
B19: Ponto de equilíbrio (unidades): | C19: =IF(rl_val>0,ct_val/(rl_val/qtd_val),0)
B21: AVALIAÇÃO PLURIANUAL (PERENES)
B22: Custo de formação anual TOTAL (R$): | C22: 0
B23: Taxa de desconto (% a.a.): | C23: 6
B25: Ano | C25: Fase | D25: Fluxo (R$) | E25: Descontado (R$) | F25: Acumulado (R$)
B26: 0 | C26: =IF(B26=0,"Implantação",IF(B26<=form_anos,"Formação",IF(B26<=form_anos+vida_util,"Produção",""))) | D26: =IF(B26=0,-invest_total,IF(B26<=form_anos,-custo_form,IF(B26<=form_anos+vida_util,rl_val-(ct_val-dep_total),0))) | E26: =IF(D26<>"",D26/(1+taxa_desc/100)^B26,0) | F26: =E26
B27: 1 | C27: =IF(B27=0,"Implantação",IF(B27<=form_anos,"Formação",IF(B27<=form_anos+vida_util,"Produção",""))) | D27: =IF(B27=0,-invest_total,IF(B27<=form_anos,-custo_form,IF(B27<=form_anos+vida_util,rl_val-(ct_val-dep_total),0))) | E27: =IF(D27<>"",D27/(1+taxa_desc/100)^B27,0) | F27: =F26+E27
B28: 2 | C28: =IF(B28=0,"Implantação",IF(B28<=form_anos,"Formação",IF(B28<=form_anos+vida_util,"Produção",""))) | D28: =IF(B28=0,-invest_total,IF(B28<=form_anos,-custo_form,IF(B28<=form_anos+vida_util,rl_val-(ct_val-dep_total),0))) | E28: =IF(D28<>"",D28/(1+taxa_desc/100)^B28,0) | F28: =F27+E28
B29: 3 | C29: =IF(B29=0,"Implantação",IF(B29<=form_anos,"Formação",IF(B29<=form_anos+vida_util,"Produção",""))) | D29: =IF(B29=0,-invest_total,IF(B29<=form_anos,-custo_form,IF(B29<=form_anos+vida_util,rl_val-(ct_val-dep_total),0))) | E29: =IF(D29<>"",D29/(1+taxa_desc/100)^B29,0) | F29: =F28+E29
B30: 4 | C30: =IF(B30=0,"Implantação",IF(B30<=form_anos,"Formação",IF(B30<=form_anos+vida_util,"Produção",""))) | D30: =IF(B30=0,-invest_total,IF(B30<=form_anos,-custo_form,IF(B30<=form_anos+vida_util,rl_val-(ct_val-dep_total),0))) | E30: =IF(D30<>"",D30/(1+taxa_desc/100)^B30,0) | F30: =F29+E30
B31: 5 | C31: =IF(B31=0,"Implantação",IF(B31<=form_anos,"Formação",IF(B31<=form_anos+vida_util,"Produção",""))) | D31: =IF(B31=0,-invest_total,IF(B31<=form_anos,-custo_form,IF(B31<=form_anos+vida_util,rl_val-(ct_val-dep_total),0))) | E31: =IF(D31<>"",D31/(1+taxa_desc/100)^B31,0) | F31: =F30+E31
B32: 6 | C32: =IF(B32=0,"Implantação",IF(B32<=form_anos,"Formação",IF(B32<=form_anos+vida_util,"Produção",""))) | D32: =IF(B32=0,-invest_total,IF(B32<=form_anos,-custo_form,IF(B32<=form_anos+vida_util,rl_val-(ct_val-dep_total),0))) | E32: =IF(D32<>"",D32/(1+taxa_desc/100)^B32,0) | F32: =F31+E32
B33: 7 | C33: =IF(B33=0,"Implantação",IF(B33<=form_anos,"Formação",IF(B33<=form_anos+vida_util,"Produção",""))) | D33: =IF(B33=0,-invest_total,IF(B33<=form_anos,-custo_form,IF(B33<=form_anos+vida_util,rl_val-(ct_val-dep_total),0))) | E33: =IF(D33<>"",D33/(1+taxa_desc/100)^B33,0) | F33: =F32+E33
B34: 8 | C34: =IF(B34=0,"Implantação",IF(B34<=form_anos,"Formação",IF(B34<=form_anos+vida_util,"Produção",""))) | D34: =IF(B34=0,-invest_total,IF(B34<=form_anos,-custo_form,IF(B34<=form_anos+vida_util,rl_val-(ct_val-dep_total),0))) | E34: =IF(D34<>"",D34/(1+taxa_desc/100)^B34,0) | F34: =F33+E34
B35: 9 | C35: =IF(B35=0,"Implantação",IF(B35<=form_anos,"Formação",IF(B35<=form_anos+vida_util,"Produção",""))) | D35: =IF(B35=0,-invest_total,IF(B35<=form_anos,-custo_form,IF(B35<=form_anos+vida_util,rl_val-(ct_val-dep_total),0))) | E35: =IF(D35<>"",D35/(1+taxa_desc/100)^B35,0) | F35: =F34+E35
B36: 10 | C36: =IF(B36=0,"Implantação",IF(B36<=form_anos,"Formação",IF(B36<=form_anos+vida_util,"Produção",""))) | D36: =IF(B36=0,-invest_total,IF(B36<=form_anos,-custo_form,IF(B36<=form_anos+vida_util,rl_val-(ct_val-dep_total),0))) | E36: =IF(D36<>"",D36/(1+taxa_desc/100)^B36,0) | F36: =F35+E36
B37: 11 | C37: =IF(B37=0,"Implantação",IF(B37<=form_anos,"Formação",IF(B37<=form_anos+vida_util,"Produção",""))) | D37: =IF(B37=0,-invest_total,IF(B37<=form_anos,-custo_form,IF(B37<=form_anos+vida_util,rl_val-(ct_val-dep_total),0))) | E37: =IF(D37<>"",D37/(1+taxa_desc/100)^B37,0) | F37: =F36+E37
B38: 12 | C38: =IF(B38=0,"Implantação",IF(B38<=form_anos,"Formação",IF(B38<=form_anos+vida_util,"Produção",""))) | D38: =IF(B38=0,-invest_total,IF(B38<=form_anos,-custo_form,IF(B38<=form_anos+vida_util,rl_val-(ct_val-dep_total),0))) | E38: =IF(D38<>"",D38/(1+taxa_desc/100)^B38,0) | F38: =F37+E38
... B65: 39 | C65: =IF(B65=0,"Implantação",IF(B65<=form_anos,"Formação",IF(B65<=form_anos+vida_util,"Produção",""))) | D65: =IF(B65=0,-invest_total,IF(B65<=form_anos,-custo_form,IF(B65<=form_anos+vida_util,rl_val-(ct_val-dep_total),0))) | E65: =IF(D65<>"",D65/(1+taxa_desc/100)^B65,0) | F65: =F64+E65
B68: VPL: | C68: =D26+NPV(taxa_desc/100,D27:D65)
B69: TIR: | C69: =IF(ISERROR(IRR(D26:D65)),"n/d",IRR(D26:D65))
B70: Payback (anos): | C70: =IF(COUNTIF(F26:F65,">=0")=0,"n/d",MATCH(TRUE,F26:F65>=0,0)-1+ABS(INDEX(F26:F65,MATCH(TRUE,F26:F65>=0,0)-1))/INDEX(E26:E65,MATCH(TRUE,F26:F65>=0,0)))
B72: NOTA: Fluxo de caixa exclui TODA depreciação (correção CRÍTICO-001).

Sheet 8.Relatorio
B1: PROJETO DE VIABILIDADE AGROPECUÁRIA
B2: =projeto_val
B4: ="Produtor: " & produtor_val
B5: ="Unidade: " & unidade_val
B6: ="Município: " & municipio_val
B7: ="Data: " & data_val
B8: ="Template: " & VLOOKUP(template_val,Ref!$A$1:$K$17,2,FALSE)
B9: ="Escala: " & TEXT(qtd_val,"#,##0.00") & " " & VLOOKUP(template_val,Ref!$A$1:$K$17,3,FALSE)
B11: DEMONSTRAÇÃO DE RESULTADO
B12: Receita Bruta: | C12: =rb_val
B13: (−) Comercialização: | C13: =comerc_rs
B14: (−) Funrural: | C14: =funrural_rs
B15: Receita Líquida: | C15: =rl_val
B16: (−) COE: | C16: =coe_total
B17: Margem Bruta: | C17: =margem_bruta
B18: (−) Fixos: | C18: =cot_val-coe_total
B19: Margem Líquida: | C19: =margem_liq
B20: (−) Fatores: | C20: =ct_val-cot_val
B21: RESULTADO: | C21: =resultado_final
B23: INDICADORES
B24: Eficiência econômica (RB/CT): | C24: =IF(ct_val>0,rb_val/ct_val,0)
B25: Lucratividade: | C25: =IF(rb_val>0,resultado_final/rb_val,0)
B26: Rentabilidade (ROI): | C26: =IF(coe_total>0,resultado_final/coe_total,0)
B27: Margem de segurança: | C27: =IF(AND(prod_val>0,B13>0),(prod_val-B13)/prod_val,0)
B29: AVALIAÇÃO PLURIANUAL (se perene)
B30: Investimento total: | C30: =invest_total
B31: VPL: | C31: =vpl_val
B32: TIR: | C32: =tir_val
B33: Cultura: | C33: =cultura_val
B34: Anos formação: | C34: =form_anos
B35: Vida útil: | C35: =vida_util
B37: Metodologia: CNA/Campo Futuro. COE → COT → CT. Números ilustrativos.
B38: NOTAS: (1) Fluxo de caixa (aba 7) exclui toda depreciação e para no fim da vida útil produtiva. (2) Área de implantação e de arrendamento herdam a área do passo 2 (Receita). (3) Ciclos por ano e mortalidade de atividades de giro não são modelados nesta planilha.
